roter/__init__.py
roter/__main__.py
roter/api.py
roter/cli.py
roter-2024.6.25.dist-info/LICENSE
roter-2024.6.25.dist-info/METADATA
roter-2024.6.25.dist-info/WHEEL
roter-2024.6.25.dist-info/entry_points.txt
roter-2024.6.25.dist-info/top_level.txt
roter-2024.6.25.dist-info/RECORD
