Metadata-Version: 2.1
Name: roter
Version: 2024.6.25
Summary: Rotate and combine tables (Danish: Roter og kombiner borde).
Author-email: Stefan Hagen <stefan@hagen.link>
Maintainer-email: Stefan Hagen <stefan@hagen.link>
License: MIT License
Project-URL: Homepage, https://git.sr.ht/~sthagen/roter
Project-URL: Bug-Tracker, https://todo.sr.ht/~sthagen/roter
Project-URL: Documentation, https://codes.dilettant.life/docs/roter
Project-URL: Source-Code, https://git.sr.ht/~sthagen/roter
Project-URL: Test-Coverage, https://codes.dilettant.life/coverage/roter
Keywords: developer-tools,text-processing,validation,verification
Classifier: Development Status :: 3 - Alpha
Classifier: Intended Audience :: Developers
Classifier: License :: OSI Approved :: MIT License
Classifier: Programming Language :: Python :: 3.10
Classifier: Programming Language :: Python :: 3.11
Classifier: Programming Language :: Python :: 3.12
Classifier: Programming Language :: Python :: 3.9
Requires-Python: >=3.9
License-File: LICENSE
Provides-Extra: dev
Requires-Dist: black ; extra == 'dev'
Requires-Dist: coverage ; extra == 'dev'
Requires-Dist: hypothesis ; extra == 'dev'
Requires-Dist: mypy ; extra == 'dev'
Requires-Dist: pytest ; extra == 'dev'
Requires-Dist: pytest-cov ; extra == 'dev'
Requires-Dist: pytest-flake8 ; extra == 'dev'
Requires-Dist: ruff ; extra == 'dev'
